{"cameraMode":{"drawMode":0,"name":"Shaded","section":"Shading Mode"},"sceneLighting":true,"audioPlay":false,"sceneViewState":{"showFog":true,"showMaterialUpdate":false,"showSkybox":true,"showFlares":true,"showImageEffects":true,"showParticleSystems":true},"in2DMode":false,"pivot":{"x":0.005021234508603811,"y":-2.2786309719085695,"z":-5.265519142150879},"rotation":{"x":0.35030412673950198,"y":-0.00280992710031569,"z":0.0010498592164367438,"w":0.9366312623023987},"size":28.67540168762207,"orthographic":false}